novo_sdk/__init__.py
novo_sdk/novo_sdk.py
novo_sdk-0.1.1.dist-info/METADATA
novo_sdk-0.1.1.dist-info/WHEEL
novo_sdk-0.1.1.dist-info/entry_points.txt
novo_sdk-0.1.1.dist-info/top_level.txt
novo_sdk-0.1.1.dist-info/RECORD
