Metadata-Version: 2.4
Name: novo_sdk
Version: 0.1.1
Summary: Novosns CLI sdk
Author-email: Li Junru <junru.li@novosns.com>
License: MIT
Requires-Python: >=3.7
